easy_wrap/__init__.py
easy_wrap/draw.py
easy_wrap-0.1.2.dist-info/METADATA
easy_wrap-0.1.2.dist-info/WHEEL
easy_wrap-0.1.2.dist-info/RECORD
