Metadata-Version: 2.1
Name: easy-wrap
Version: 0.1.2
Summary: 
Home-page: https://github.com/bridgeL/easy_wrap
Author: Su
Author-email: wxlxy316@163.com
Requires-Python: >=3.8,<4.0
Classifier: Programming Language :: Python :: 3
Classifier: Programming Language :: Python :: 3.8
Classifier: Programming Language :: Python :: 3.9
Classifier: Programming Language :: Python :: 3.10
Classifier: Programming Language :: Python :: 3.11
Requires-Dist: pillow (>=9.4.0,<10.0.0)
Project-URL: Repository, https://github.com/bridgeL/easy_wrap
